pub/tools/__init__.py
pub/tools/citations.py
pub/tools/config.py
pub/tools/cooking.py
pub/tools/entrez.py
pub/tools/formatting.py
pub/tools/isbn.py
pub/tools/journals.json
pub/tools/journals.py
pub/tools/orcid.py
pub/tools/schema.py
pub.tools-5.3.0.dist-info/METADATA
pub.tools-5.3.0.dist-info/WHEEL
pub.tools-5.3.0.dist-info/RECORD
