Metadata-Version: 2.4
Name: pub.tools
Version: 5.3.0
Summary: Get publication metadata from NCBI's eUtils and generate citations.
Project-URL: homepage, https://github.com/imsweb/pub.tools
Project-URL: documentation, https://imsweb.github.io/pub.tools
Author-email: Eric Wohnlich <wohnlice@imsweb.com>
License: GPL
Classifier: Programming Language :: Python :: 3
Classifier: Topic :: Scientific/Engineering
Classifier: Topic :: Scientific/Engineering :: Bio-Informatics
Classifier: Topic :: Software Development :: Libraries :: Python Modules
Requires-Python: >=3.11
Requires-Dist: beautifulsoup4
Requires-Dist: biopython>=1.83
Requires-Dist: deprecation
Requires-Dist: lxml
Requires-Dist: requests
Requires-Dist: unidecode
Provides-Extra: test
Requires-Dist: pytest; extra == 'test'
